[
  {
    "Type": "AkAudioEvent",
    "Name": "enter_wild_level_lz_room_small_normal",
    "Flags": "RF_Public | RF_Transactional | RF_WasLoaded | RF_LoadCompleted",
    "Class": "UScriptClass'AkAudioEvent'",
    "EventCookedData": {
      "EventLanguageMap": [
        {
          "Key": {
            "LanguageId": 0,
            "LanguageName": "SFX",
            "LanguageRequirement": "EWwiseLanguageRequirement::SFX"
          },
          "Value": {
            "EventId": -175920760,
            "SoundBanks": [
              {
                "SoundBankId": -175920760,
                "SoundBankPathName": "Event/enter_wild_level_lz_room_small_normal.bnk",
                "MemoryAlignment": 16,
                "bDeviceMemory": false,
                "bContainsMedia": false,
                "SoundBankType": "EWwiseSoundBankType::Event",
                "DebugName": "enter_wild_level_lz_room_small_normal",
                "PackagedFile": null
              }
            ],
            "Media": [],
            "ExternalSources": [],
            "SwitchContainerLeaves": [],
            "RequiredGroupValueSet": [
              {
                "Type": "EWwiseGroupType::State",
                "GroupId": 143585452,
                "Id": 748895195,
                "DebugName": "None"
              },
              {
                "Type": "EWwiseGroupType::State",
                "GroupId": 1684817153,
                "Id": 1101306714,
                "DebugName": "no_level_lz_small_normal"
              }
            ],
            "DestroyOptions": "EWwiseEventDestroyOptions::StopEventOnDestroy",
            "DebugName": "enter_wild_level_lz_room_small_normal"
          }
        }
      ],
      "DebugName": "enter_wild_level_lz_room_small_normal",
      "EventId": -175920760
    },
    "MaximumDuration": 0.0,
    "MinimumDuration": 0.0,
    "IsInfinite": false,
    "MaxAttenuationRadius": 0.0
  }
]