[
  {
    "Type": "AkAudioEvent",
    "Name": "play_vo_zuoyequnxing_83_nosub_01",
    "Flags": "RF_Public | RF_Transactional | RF_WasLoaded | RF_LoadCompleted",
    "Class": "UScriptClass'AkAudioEvent'",
    "Package": "Client/Content/Aki/WwiseAudio/Events/play_vo_zuoyequnxing_83_nosub_01",
    "EventCookedData": {
      "EventLanguageMap": [
        {
          "Key": {
            "LanguageId": 1819748192,
            "LanguageName": "en",
            "LanguageRequirement": "EWwiseLanguageRequirement::IsOptional"
          },
          "Value": {
            "EventId": 3569151320,
            "SoundBanks": [
              {
                "SoundBankId": 3569151320,
                "SoundBankPathName": "Event/en/play_vo_zuoyequnxing_83_nosub_01.bnk",
                "MemoryAlignment": 16,
                "bDeviceMemory": false,
                "bContainsMedia": false,
                "SoundBankType": "EWwiseSoundBankType::Event",
                "DebugName": "play_vo_zuoyequnxing_83_nosub_01",
                "PackagedFile": null
              }
            ],
            "Media": [
              {
                "MediaId": 703755676,
                "MediaPathName": "Media/en/703755676.wem",
                "PrefetchSize": 0,
                "MemoryAlignment": 16,
                "bDeviceMemory": false,
                "bStreaming": true,
                "DebugName": "plot\\3.3\\level_b\\en_vo_Zuoyequnxing_83_NOSUB_01.wav",
                "PackagedFile": null
              }
            ],
            "ExternalSources": [],
            "SwitchContainerLeaves": [],
            "RequiredGroupValueSet": [],
            "DestroyOptions": "EWwiseEventDestroyOptions::StopEventOnDestroy",
            "DebugName": "play_vo_zuoyequnxing_83_nosub_01"
          }
        },
        {
          "Key": {
            "LanguageId": 1735860046,
            "LanguageName": "ja",
            "LanguageRequirement": "EWwiseLanguageRequirement::IsOptional"
          },
          "Value": {
            "EventId": 3569151320,
            "SoundBanks": [
              {
                "SoundBankId": 3569151320,
                "SoundBankPathName": "Event/ja/play_vo_zuoyequnxing_83_nosub_01.bnk",
                "MemoryAlignment": 16,
                "bDeviceMemory": false,
                "bContainsMedia": false,
                "SoundBankType": "EWwiseSoundBankType::Event",
                "DebugName": "play_vo_zuoyequnxing_83_nosub_01",
                "PackagedFile": null
              }
            ],
            "Media": [
              {
                "MediaId": 533414051,
                "MediaPathName": "Media/ja/533414051.wem",
                "PrefetchSize": 0,
                "MemoryAlignment": 16,
                "bDeviceMemory": false,
                "bStreaming": true,
                "DebugName": "plot\\3.3\\level_b\\ja_vo_Zuoyequnxing_83_NOSUB_01.wav",
                "PackagedFile": null
              }
            ],
            "ExternalSources": [],
            "SwitchContainerLeaves": [],
            "RequiredGroupValueSet": [],
            "DestroyOptions": "EWwiseEventDestroyOptions::StopEventOnDestroy",
            "DebugName": "play_vo_zuoyequnxing_83_nosub_01"
          }
        },
        {
          "Key": {
            "LanguageId": 1719082483,
            "LanguageName": "ko",
            "LanguageRequirement": "EWwiseLanguageRequirement::IsOptional"
          },
          "Value": {
            "EventId": 3569151320,
            "SoundBanks": [
              {
                "SoundBankId": 3569151320,
                "SoundBankPathName": "Event/ko/play_vo_zuoyequnxing_83_nosub_01.bnk",
                "MemoryAlignment": 16,
                "bDeviceMemory": false,
                "bContainsMedia": false,
                "SoundBankType": "EWwiseSoundBankType::Event",
                "DebugName": "play_vo_zuoyequnxing_83_nosub_01",
                "PackagedFile": null
              }
            ],
            "Media": [
              {
                "MediaId": 513031401,
                "MediaPathName": "Media/ko/513031401.wem",
                "PrefetchSize": 0,
                "MemoryAlignment": 16,
                "bDeviceMemory": false,
                "bStreaming": true,
                "DebugName": "plot\\3.3\\level_b\\ko_vo_Zuoyequnxing_83_NOSUB_01.wav",
                "PackagedFile": null
              }
            ],
            "ExternalSources": [],
            "SwitchContainerLeaves": [],
            "RequiredGroupValueSet": [],
            "DestroyOptions": "EWwiseEventDestroyOptions::StopEventOnDestroy",
            "DebugName": "play_vo_zuoyequnxing_83_nosub_01"
          }
        },
        {
          "Key": {
            "LanguageId": 1467418007,
            "LanguageName": "zh",
            "LanguageRequirement": "EWwiseLanguageRequirement::IsDefault"
          },
          "Value": {
            "EventId": 3569151320,
            "SoundBanks": [
              {
                "SoundBankId": 3569151320,
                "SoundBankPathName": "Event/zh/play_vo_zuoyequnxing_83_nosub_01.bnk",
                "MemoryAlignment": 16,
                "bDeviceMemory": false,
                "bContainsMedia": false,
                "SoundBankType": "EWwiseSoundBankType::Event",
                "DebugName": "play_vo_zuoyequnxing_83_nosub_01",
                "PackagedFile": null
              }
            ],
            "Media": [
              {
                "MediaId": 222344810,
                "MediaPathName": "Media/zh/222344810.wem",
                "PrefetchSize": 0,
                "MemoryAlignment": 16,
                "bDeviceMemory": false,
                "bStreaming": true,
                "DebugName": "plot\\3.3\\level_b\\zh_vo_Zuoyequnxing_83_NOSUB_01.wav",
                "PackagedFile": null
              }
            ],
            "ExternalSources": [],
            "SwitchContainerLeaves": [],
            "RequiredGroupValueSet": [],
            "DestroyOptions": "EWwiseEventDestroyOptions::StopEventOnDestroy",
            "DebugName": "play_vo_zuoyequnxing_83_nosub_01"
          }
        }
      ],
      "DebugName": "play_vo_zuoyequnxing_83_nosub_01",
      "EventId": 3569151320
    },
    "MaximumDuration": 1.8373333,
    "MinimumDuration": 1.8373333,
    "IsInfinite": false,
    "MaxAttenuationRadius": 0.0
  }
]