[
  {
    "Type": "AkAudioEvent",
    "Name": "play_vo_kelaita_com_jump",
    "Flags": "RF_Public | RF_Transactional | RF_WasLoaded | RF_LoadCompleted",
    "Class": "UScriptClass'AkAudioEvent'",
    "EventCookedData": {
      "EventLanguageMap": [
        {
          "Key": {
            "LanguageId": 1819748192,
            "LanguageName": "en",
            "LanguageRequirement": "EWwiseLanguageRequirement::IsOptional"
          },
          "Value": {
            "EventId": 1510744550,
            "SoundBanks": [
              {
                "SoundBankId": 1510744550,
                "SoundBankPathName": "Event/en/play_vo_kelaita_com_jump.bnk",
                "MemoryAlignment": 16,
                "bDeviceMemory": false,
                "bContainsMedia": false,
                "SoundBankType": "EWwiseSoundBankType::Event",
                "DebugName": "play_vo_kelaita_com_jump",
                "PackagedFile": null
              }
            ],
            "Media": [
              {
                "MediaId": 944174353,
                "MediaPathName": "Media/en/944174353.wem",
                "PrefetchSize": 0,
                "MemoryAlignment": 16,
                "bDeviceMemory": false,
                "bStreaming": true,
                "DebugName": "role\\branch_2.0\\kelaita\\en_vo_kelaita_com_jump_01_tone.wav",
                "PackagedFile": null
              },
              {
                "MediaId": 948964533,
                "MediaPathName": "Media/en/948964533.wem",
                "PrefetchSize": 0,
                "MemoryAlignment": 16,
                "bDeviceMemory": false,
                "bStreaming": true,
                "DebugName": "role\\branch_2.0\\kelaita\\en_vo_kelaita_com_jump_03_tone.wav",
                "PackagedFile": null
              },
              {
                "MediaId": 1047509313,
                "MediaPathName": "Media/en/1047509313.wem",
                "PrefetchSize": 0,
                "MemoryAlignment": 16,
                "bDeviceMemory": false,
                "bStreaming": true,
                "DebugName": "role\\branch_2.0\\kelaita\\en_vo_kelaita_com_jump_02_tone.wav",
                "PackagedFile": null
              }
            ],
            "ExternalSources": [],
            "SwitchContainerLeaves": [],
            "RequiredGroupValueSet": [],
            "DestroyOptions": "EWwiseEventDestroyOptions::StopEventOnDestroy",
            "DebugName": "play_vo_kelaita_com_jump"
          }
        },
        {
          "Key": {
            "LanguageId": 1735860046,
            "LanguageName": "ja",
            "LanguageRequirement": "EWwiseLanguageRequirement::IsOptional"
          },
          "Value": {
            "EventId": 1510744550,
            "SoundBanks": [
              {
                "SoundBankId": 1510744550,
                "SoundBankPathName": "Event/ja/play_vo_kelaita_com_jump.bnk",
                "MemoryAlignment": 16,
                "bDeviceMemory": false,
                "bContainsMedia": false,
                "SoundBankType": "EWwiseSoundBankType::Event",
                "DebugName": "play_vo_kelaita_com_jump",
                "PackagedFile": null
              }
            ],
            "Media": [
              {
                "MediaId": 261711822,
                "MediaPathName": "Media/ja/261711822.wem",
                "PrefetchSize": 0,
                "MemoryAlignment": 16,
                "bDeviceMemory": false,
                "bStreaming": true,
                "DebugName": "role\\branch_2.0\\kelaita\\ja_vo_kelaita_com_jump_02_tone.wav",
                "PackagedFile": null
              },
              {
                "MediaId": 647721486,
                "MediaPathName": "Media/ja/647721486.wem",
                "PrefetchSize": 0,
                "MemoryAlignment": 16,
                "bDeviceMemory": false,
                "bStreaming": true,
                "DebugName": "role\\branch_2.0\\kelaita\\ja_vo_kelaita_com_jump_01_tone.wav",
                "PackagedFile": null
              },
              {
                "MediaId": 669949960,
                "MediaPathName": "Media/ja/669949960.wem",
                "PrefetchSize": 0,
                "MemoryAlignment": 16,
                "bDeviceMemory": false,
                "bStreaming": true,
                "DebugName": "role\\branch_2.0\\kelaita\\ja_vo_kelaita_com_jump_03_tone.wav",
                "PackagedFile": null
              }
            ],
            "ExternalSources": [],
            "SwitchContainerLeaves": [],
            "RequiredGroupValueSet": [],
            "DestroyOptions": "EWwiseEventDestroyOptions::StopEventOnDestroy",
            "DebugName": "play_vo_kelaita_com_jump"
          }
        },
        {
          "Key": {
            "LanguageId": 1719082483,
            "LanguageName": "ko",
            "LanguageRequirement": "EWwiseLanguageRequirement::IsOptional"
          },
          "Value": {
            "EventId": 1510744550,
            "SoundBanks": [
              {
                "SoundBankId": 1510744550,
                "SoundBankPathName": "Event/ko/play_vo_kelaita_com_jump.bnk",
                "MemoryAlignment": 16,
                "bDeviceMemory": false,
                "bContainsMedia": false,
                "SoundBankType": "EWwiseSoundBankType::Event",
                "DebugName": "play_vo_kelaita_com_jump",
                "PackagedFile": null
              }
            ],
            "Media": [
              {
                "MediaId": 4511143,
                "MediaPathName": "Media/ko/4511143.wem",
                "PrefetchSize": 0,
                "MemoryAlignment": 16,
                "bDeviceMemory": false,
                "bStreaming": true,
                "DebugName": "role\\branch_2.0\\kelaita\\ko_vo_kelaita_com_jump_01_tone.wav",
                "PackagedFile": null
              },
              {
                "MediaId": 247112278,
                "MediaPathName": "Media/ko/247112278.wem",
                "PrefetchSize": 0,
                "MemoryAlignment": 16,
                "bDeviceMemory": false,
                "bStreaming": true,
                "DebugName": "role\\branch_2.0\\kelaita\\ko_vo_kelaita_com_jump_03_tone.wav",
                "PackagedFile": null
              },
              {
                "MediaId": 976541049,
                "MediaPathName": "Media/ko/976541049.wem",
                "PrefetchSize": 0,
                "MemoryAlignment": 16,
                "bDeviceMemory": false,
                "bStreaming": true,
                "DebugName": "role\\branch_2.0\\kelaita\\ko_vo_kelaita_com_jump_02_tone.wav",
                "PackagedFile": null
              }
            ],
            "ExternalSources": [],
            "SwitchContainerLeaves": [],
            "RequiredGroupValueSet": [],
            "DestroyOptions": "EWwiseEventDestroyOptions::StopEventOnDestroy",
            "DebugName": "play_vo_kelaita_com_jump"
          }
        },
        {
          "Key": {
            "LanguageId": 1467418007,
            "LanguageName": "zh",
            "LanguageRequirement": "EWwiseLanguageRequirement::IsDefault"
          },
          "Value": {
            "EventId": 1510744550,
            "SoundBanks": [
              {
                "SoundBankId": 1510744550,
                "SoundBankPathName": "Event/zh/play_vo_kelaita_com_jump.bnk",
                "MemoryAlignment": 16,
                "bDeviceMemory": false,
                "bContainsMedia": false,
                "SoundBankType": "EWwiseSoundBankType::Event",
                "DebugName": "play_vo_kelaita_com_jump",
                "PackagedFile": null
              }
            ],
            "Media": [
              {
                "MediaId": 54883776,
                "MediaPathName": "Media/zh/54883776.wem",
                "PrefetchSize": 0,
                "MemoryAlignment": 16,
                "bDeviceMemory": false,
                "bStreaming": true,
                "DebugName": "role\\branch_2.0\\kelaita\\zh_vo_kelaita_com_jump_03_tone.wav",
                "PackagedFile": null
              },
              {
                "MediaId": 385531116,
                "MediaPathName": "Media/zh/385531116.wem",
                "PrefetchSize": 0,
                "MemoryAlignment": 16,
                "bDeviceMemory": false,
                "bStreaming": true,
                "DebugName": "role\\branch_2.0\\kelaita\\zh_vo_kelaita_com_jump_01_tone.wav",
                "PackagedFile": null
              },
              {
                "MediaId": 829941763,
                "MediaPathName": "Media/zh/829941763.wem",
                "PrefetchSize": 0,
                "MemoryAlignment": 16,
                "bDeviceMemory": false,
                "bStreaming": true,
                "DebugName": "role\\branch_2.0\\kelaita\\zh_vo_kelaita_com_jump_02_tone.wav",
                "PackagedFile": null
              }
            ],
            "ExternalSources": [],
            "SwitchContainerLeaves": [],
            "RequiredGroupValueSet": [],
            "DestroyOptions": "EWwiseEventDestroyOptions::StopEventOnDestroy",
            "DebugName": "play_vo_kelaita_com_jump"
          }
        }
      ],
      "DebugName": "play_vo_kelaita_com_jump",
      "EventId": 1510744550
    },
    "MaximumDuration": 0.23547916,
    "MinimumDuration": 0.20558333,
    "IsInfinite": false,
    "MaxAttenuationRadius": 5000.0
  }
]