[
  {
    "Type": "AkAudioEvent",
    "Name": "play_favor_word_katixiya_sys_about_lupa",
    "Flags": "RF_Public | RF_Transactional | RF_WasLoaded | RF_LoadCompleted",
    "Class": "UScriptClass'AkAudioEvent'",
    "Package": "Client/Content/Aki/WwiseAudio/Events/play_favor_word_katixiya_sys_about_lupa",
    "EventCookedData": {
      "EventLanguageMap": [
        {
          "Key": {
            "LanguageId": 0,
            "LanguageName": "SFX",
            "LanguageRequirement": "EWwiseLanguageRequirement::SFX"
          },
          "Value": {
            "EventId": 2526154229,
            "SoundBanks": [
              {
                "SoundBankId": 2526154229,
                "SoundBankPathName": "Event/play_favor_word_katixiya_sys_about_lupa.bnk",
                "MemoryAlignment": 16,
                "bDeviceMemory": false,
                "bContainsMedia": false,
                "SoundBankType": "EWwiseSoundBankType::Event",
                "DebugName": "play_favor_word_katixiya_sys_about_lupa",
                "PackagedFile": null
              }
            ],
            "Media": [
              {
                "MediaId": 473722750,
                "MediaPathName": "Media/473722750.wem",
                "PrefetchSize": 0,
                "MemoryAlignment": 16,
                "bDeviceMemory": false,
                "bStreaming": true,
                "DebugName": "Voices\\ko\\role\\branch_2,4\\katixiya\\ko_vo_katixiya_sys_about_lupa_word.wav",
                "PackagedFile": null
              },
              {
                "MediaId": 1027667166,
                "MediaPathName": "Media/1027667166.wem",
                "PrefetchSize": 0,
                "MemoryAlignment": 16,
                "bDeviceMemory": false,
                "bStreaming": true,
                "DebugName": "Voices\\zh\\role\\branch_2,4\\katixiya\\zh_vo_katixiya_sys_about_lupa_word.wav",
                "PackagedFile": null
              },
              {
                "MediaId": 108157897,
                "MediaPathName": "Media/108157897.wem",
                "PrefetchSize": 0,
                "MemoryAlignment": 16,
                "bDeviceMemory": false,
                "bStreaming": true,
                "DebugName": "Voices\\en\\role\\branch_2,4\\katixiya\\en_vo_katixiya_sys_about_lupa_word.wav",
                "PackagedFile": null
              },
              {
                "MediaId": 521256747,
                "MediaPathName": "Media/521256747.wem",
                "PrefetchSize": 0,
                "MemoryAlignment": 16,
                "bDeviceMemory": false,
                "bStreaming": true,
                "DebugName": "Voices\\ja\\role\\branch_2,4\\katixiya\\ja_vo_katixiya_sys_about_lupa_word.wav",
                "PackagedFile": null
              }
            ],
            "ExternalSources": [],
            "SwitchContainerLeaves": [],
            "RequiredGroupValueSet": [],
            "DestroyOptions": "EWwiseEventDestroyOptions::StopEventOnDestroy",
            "DebugName": "play_favor_word_katixiya_sys_about_lupa"
          }
        }
      ],
      "DebugName": "play_favor_word_katixiya_sys_about_lupa",
      "EventId": 2526154229
    },
    "MaximumDuration": 37.19325,
    "MinimumDuration": 27.388563,
    "IsInfinite": false,
    "MaxAttenuationRadius": 0.0
  }
]