[
  {
    "Type": "AkAudioEvent",
    "Name": "play_plot_general_foley_soft_05",
    "Flags": "RF_Public | RF_Transactional | RF_WasLoaded | RF_LoadCompleted",
    "Class": "UScriptClass'AkAudioEvent'",
    "EventCookedData": {
      "EventLanguageMap": [
        {
          "Key": {
            "LanguageId": 0,
            "LanguageName": "SFX",
            "LanguageRequirement": "EWwiseLanguageRequirement::SFX"
          },
          "Value": {
            "EventId": 1957268233,
            "SoundBanks": [
              {
                "SoundBankId": 1957268233,
                "SoundBankPathName": "Event/play_plot_general_foley_soft_05.bnk",
                "MemoryAlignment": 16,
                "bDeviceMemory": false,
                "bContainsMedia": false,
                "SoundBankType": "EWwiseSoundBankType::Event",
                "DebugName": "play_plot_general_foley_soft_05",
                "PackagedFile": null
              }
            ],
            "Media": [
              {
                "MediaId": 154830453,
                "MediaPathName": "Media/154830453.wem",
                "PrefetchSize": 0,
                "MemoryAlignment": 16,
                "bDeviceMemory": false,
                "bStreaming": false,
                "DebugName": "role\\role_bat_foley\\plot_general_foley\\soft\\plot_general_foley_soft_44.wav",
                "PackagedFile": null
              },
              {
                "MediaId": 204932265,
                "MediaPathName": "Media/204932265.wem",
                "PrefetchSize": 0,
                "MemoryAlignment": 16,
                "bDeviceMemory": false,
                "bStreaming": false,
                "DebugName": "role\\role_bat_foley\\plot_general_foley\\soft\\plot_general_foley_soft_43.wav",
                "PackagedFile": null
              },
              {
                "MediaId": 380332812,
                "MediaPathName": "Media/380332812.wem",
                "PrefetchSize": 0,
                "MemoryAlignment": 16,
                "bDeviceMemory": false,
                "bStreaming": false,
                "DebugName": "role\\role_bat_foley\\plot_general_foley\\soft\\plot_general_foley_soft_50.wav",
                "PackagedFile": null
              },
              {
                "MediaId": 695582363,
                "MediaPathName": "Media/695582363.wem",
                "PrefetchSize": 0,
                "MemoryAlignment": 16,
                "bDeviceMemory": false,
                "bStreaming": false,
                "DebugName": "role\\role_bat_foley\\plot_general_foley\\soft\\plot_general_foley_soft_45.wav",
                "PackagedFile": null
              },
              {
                "MediaId": 931753683,
                "MediaPathName": "Media/931753683.wem",
                "PrefetchSize": 0,
                "MemoryAlignment": 16,
                "bDeviceMemory": false,
                "bStreaming": false,
                "DebugName": "role\\role_bat_foley\\plot_general_foley\\soft\\plot_general_foley_soft_38.wav",
                "PackagedFile": null
              }
            ],
            "ExternalSources": [],
            "SwitchContainerLeaves": [],
            "RequiredGroupValueSet": [],
            "DestroyOptions": "EWwiseEventDestroyOptions::StopEventOnDestroy",
            "DebugName": "play_plot_general_foley_soft_05"
          }
        }
      ],
      "DebugName": "play_plot_general_foley_soft_05",
      "EventId": 1957268233
    },
    "MaximumDuration": 1.2882917,
    "MinimumDuration": 0.85361785,
    "IsInfinite": false,
    "MaxAttenuationRadius": 0.0
  }
]