[
  {
    "Type": "AkAudioEvent",
    "Name": "play_favor_word_yuanwu_skill_02",
    "Flags": "RF_Public | RF_Transactional | RF_WasLoaded | RF_LoadCompleted",
    "Class": "UScriptClass'AkAudioEvent'",
    "EventCookedData": {
      "EventLanguageMap": [
        {
          "Key": {
            "LanguageId": 1819748192,
            "LanguageName": "en",
            "LanguageRequirement": "EWwiseLanguageRequirement::IsOptional"
          },
          "Value": {
            "EventId": 138102254,
            "SoundBanks": [
              {
                "SoundBankId": 138102254,
                "SoundBankPathName": "Event/en/play_favor_word_yuanwu_skill_02.bnk",
                "MemoryAlignment": 16,
                "bDeviceMemory": false,
                "bContainsMedia": false,
                "SoundBankType": "EWwiseSoundBankType::Event",
                "DebugName": "play_favor_word_yuanwu_skill_02",
                "PackagedFile": null
              }
            ],
            "Media": [
              {
                "MediaId": 1039772878,
                "MediaPathName": "Media/en/1039772878.wem",
                "PrefetchSize": 0,
                "MemoryAlignment": 16,
                "bDeviceMemory": false,
                "bStreaming": true,
                "DebugName": "role\\branch_1_0\\yuanwu\\vo_yuanwu_skill_02.wav",
                "PackagedFile": null
              }
            ],
            "ExternalSources": [],
            "SwitchContainerLeaves": [],
            "RequiredGroupValueSet": [],
            "DestroyOptions": "EWwiseEventDestroyOptions::StopEventOnDestroy",
            "DebugName": "play_favor_word_yuanwu_skill_02"
          }
        },
        {
          "Key": {
            "LanguageId": 1735860046,
            "LanguageName": "ja",
            "LanguageRequirement": "EWwiseLanguageRequirement::IsOptional"
          },
          "Value": {
            "EventId": 138102254,
            "SoundBanks": [
              {
                "SoundBankId": 138102254,
                "SoundBankPathName": "Event/ja/play_favor_word_yuanwu_skill_02.bnk",
                "MemoryAlignment": 16,
                "bDeviceMemory": false,
                "bContainsMedia": false,
                "SoundBankType": "EWwiseSoundBankType::Event",
                "DebugName": "play_favor_word_yuanwu_skill_02",
                "PackagedFile": null
              }
            ],
            "Media": [
              {
                "MediaId": 1031726215,
                "MediaPathName": "Media/ja/1031726215.wem",
                "PrefetchSize": 0,
                "MemoryAlignment": 16,
                "bDeviceMemory": false,
                "bStreaming": true,
                "DebugName": "role\\branch_1_0\\yuanwu\\vo_yuanwu_skill_02.wav",
                "PackagedFile": null
              }
            ],
            "ExternalSources": [],
            "SwitchContainerLeaves": [],
            "RequiredGroupValueSet": [],
            "DestroyOptions": "EWwiseEventDestroyOptions::StopEventOnDestroy",
            "DebugName": "play_favor_word_yuanwu_skill_02"
          }
        },
        {
          "Key": {
            "LanguageId": 1719082483,
            "LanguageName": "ko",
            "LanguageRequirement": "EWwiseLanguageRequirement::IsOptional"
          },
          "Value": {
            "EventId": 138102254,
            "SoundBanks": [
              {
                "SoundBankId": 138102254,
                "SoundBankPathName": "Event/ko/play_favor_word_yuanwu_skill_02.bnk",
                "MemoryAlignment": 16,
                "bDeviceMemory": false,
                "bContainsMedia": false,
                "SoundBankType": "EWwiseSoundBankType::Event",
                "DebugName": "play_favor_word_yuanwu_skill_02",
                "PackagedFile": null
              }
            ],
            "Media": [
              {
                "MediaId": 725823490,
                "MediaPathName": "Media/ko/725823490.wem",
                "PrefetchSize": 0,
                "MemoryAlignment": 16,
                "bDeviceMemory": false,
                "bStreaming": true,
                "DebugName": "role\\branch_1_0\\yuanwu\\vo_yuanwu_skill_02.wav",
                "PackagedFile": null
              }
            ],
            "ExternalSources": [],
            "SwitchContainerLeaves": [],
            "RequiredGroupValueSet": [],
            "DestroyOptions": "EWwiseEventDestroyOptions::StopEventOnDestroy",
            "DebugName": "play_favor_word_yuanwu_skill_02"
          }
        },
        {
          "Key": {
            "LanguageId": 1467418007,
            "LanguageName": "zh",
            "LanguageRequirement": "EWwiseLanguageRequirement::IsDefault"
          },
          "Value": {
            "EventId": 138102254,
            "SoundBanks": [
              {
                "SoundBankId": 138102254,
                "SoundBankPathName": "Event/zh/play_favor_word_yuanwu_skill_02.bnk",
                "MemoryAlignment": 16,
                "bDeviceMemory": false,
                "bContainsMedia": false,
                "SoundBankType": "EWwiseSoundBankType::Event",
                "DebugName": "play_favor_word_yuanwu_skill_02",
                "PackagedFile": null
              }
            ],
            "Media": [
              {
                "MediaId": 499351551,
                "MediaPathName": "Media/zh/499351551.wem",
                "PrefetchSize": 0,
                "MemoryAlignment": 16,
                "bDeviceMemory": false,
                "bStreaming": true,
                "DebugName": "role\\branch_1_0\\yuanwu\\vo_yuanwu_skill_02.wav",
                "PackagedFile": null
              }
            ],
            "ExternalSources": [],
            "SwitchContainerLeaves": [],
            "RequiredGroupValueSet": [],
            "DestroyOptions": "EWwiseEventDestroyOptions::StopEventOnDestroy",
            "DebugName": "play_favor_word_yuanwu_skill_02"
          }
        }
      ],
      "DebugName": "play_favor_word_yuanwu_skill_02",
      "EventId": 138102254
    },
    "MaximumDuration": 1.198625,
    "MinimumDuration": 1.198625,
    "IsInfinite": false,
    "MaxAttenuationRadius": 0.0
  }
]