[
  {
    "Type": "AkAudioEvent",
    "Name": "play_vo_katixiya_sys_jointeam",
    "Flags": "RF_Public | RF_Transactional | RF_WasLoaded | RF_LoadCompleted",
    "Class": "UScriptClass'AkAudioEvent'",
    "Package": "Client/Content/Aki/WwiseAudio/Events/play_vo_katixiya_sys_jointeam",
    "EventCookedData": {
      "EventLanguageMap": [
        {
          "Key": {
            "LanguageId": 1819748192,
            "LanguageName": "en",
            "LanguageRequirement": "EWwiseLanguageRequirement::IsOptional"
          },
          "Value": {
            "EventId": 2827152122,
            "SoundBanks": [
              {
                "SoundBankId": 2827152122,
                "SoundBankPathName": "Event/en/play_vo_katixiya_sys_jointeam.bnk",
                "MemoryAlignment": 16,
                "bDeviceMemory": false,
                "bContainsMedia": false,
                "SoundBankType": "EWwiseSoundBankType::Event",
                "DebugName": "play_vo_katixiya_sys_jointeam",
                "PackagedFile": null
              }
            ],
            "Media": [
              {
                "MediaId": 221776758,
                "MediaPathName": "Media/en/221776758.wem",
                "PrefetchSize": 0,
                "MemoryAlignment": 16,
                "bDeviceMemory": false,
                "bStreaming": true,
                "DebugName": "role\\branch_2,4\\katixiya\\en_vo_katixiya_sys_jointeam_03_word.wav",
                "PackagedFile": null
              },
              {
                "MediaId": 251560638,
                "MediaPathName": "Media/en/251560638.wem",
                "PrefetchSize": 0,
                "MemoryAlignment": 16,
                "bDeviceMemory": false,
                "bStreaming": true,
                "DebugName": "role\\branch_2,4\\katixiya\\en_vo_katixiya_sys_jointeam_02_word.wav",
                "PackagedFile": null
              },
              {
                "MediaId": 610628034,
                "MediaPathName": "Media/610628034.wem",
                "PrefetchSize": 0,
                "MemoryAlignment": 16,
                "bDeviceMemory": false,
                "bStreaming": true,
                "DebugName": "SFX\\UI\\sfx_ui_com\\ui_fx_spl_team_role_choose1.wav",
                "PackagedFile": null
              },
              {
                "MediaId": 841133929,
                "MediaPathName": "Media/en/841133929.wem",
                "PrefetchSize": 0,
                "MemoryAlignment": 16,
                "bDeviceMemory": false,
                "bStreaming": true,
                "DebugName": "role\\branch_2,4\\katixiya\\en_vo_katixiya_sys_jointeam_01_word.wav",
                "PackagedFile": null
              }
            ],
            "ExternalSources": [],
            "SwitchContainerLeaves": [],
            "RequiredGroupValueSet": [],
            "DestroyOptions": "EWwiseEventDestroyOptions::StopEventOnDestroy",
            "DebugName": "play_vo_katixiya_sys_jointeam"
          }
        },
        {
          "Key": {
            "LanguageId": 1735860046,
            "LanguageName": "ja",
            "LanguageRequirement": "EWwiseLanguageRequirement::IsOptional"
          },
          "Value": {
            "EventId": 2827152122,
            "SoundBanks": [
              {
                "SoundBankId": 2827152122,
                "SoundBankPathName": "Event/ja/play_vo_katixiya_sys_jointeam.bnk",
                "MemoryAlignment": 16,
                "bDeviceMemory": false,
                "bContainsMedia": false,
                "SoundBankType": "EWwiseSoundBankType::Event",
                "DebugName": "play_vo_katixiya_sys_jointeam",
                "PackagedFile": null
              }
            ],
            "Media": [
              {
                "MediaId": 31389614,
                "MediaPathName": "Media/ja/31389614.wem",
                "PrefetchSize": 0,
                "MemoryAlignment": 16,
                "bDeviceMemory": false,
                "bStreaming": true,
                "DebugName": "role\\branch_2,4\\katixiya\\ja_vo_katixiya_sys_jointeam_01_word.wav",
                "PackagedFile": null
              },
              {
                "MediaId": 300954636,
                "MediaPathName": "Media/ja/300954636.wem",
                "PrefetchSize": 0,
                "MemoryAlignment": 16,
                "bDeviceMemory": false,
                "bStreaming": true,
                "DebugName": "role\\branch_2,4\\katixiya\\ja_vo_katixiya_sys_jointeam_03_word.wav",
                "PackagedFile": null
              },
              {
                "MediaId": 385585036,
                "MediaPathName": "Media/ja/385585036.wem",
                "PrefetchSize": 0,
                "MemoryAlignment": 16,
                "bDeviceMemory": false,
                "bStreaming": true,
                "DebugName": "role\\branch_2,4\\katixiya\\ja_vo_katixiya_sys_jointeam_02_word.wav",
                "PackagedFile": null
              },
              {
                "MediaId": 610628034,
                "MediaPathName": "Media/610628034.wem",
                "PrefetchSize": 0,
                "MemoryAlignment": 16,
                "bDeviceMemory": false,
                "bStreaming": true,
                "DebugName": "SFX\\UI\\sfx_ui_com\\ui_fx_spl_team_role_choose1.wav",
                "PackagedFile": null
              }
            ],
            "ExternalSources": [],
            "SwitchContainerLeaves": [],
            "RequiredGroupValueSet": [],
            "DestroyOptions": "EWwiseEventDestroyOptions::StopEventOnDestroy",
            "DebugName": "play_vo_katixiya_sys_jointeam"
          }
        },
        {
          "Key": {
            "LanguageId": 1719082483,
            "LanguageName": "ko",
            "LanguageRequirement": "EWwiseLanguageRequirement::IsOptional"
          },
          "Value": {
            "EventId": 2827152122,
            "SoundBanks": [
              {
                "SoundBankId": 2827152122,
                "SoundBankPathName": "Event/ko/play_vo_katixiya_sys_jointeam.bnk",
                "MemoryAlignment": 16,
                "bDeviceMemory": false,
                "bContainsMedia": false,
                "SoundBankType": "EWwiseSoundBankType::Event",
                "DebugName": "play_vo_katixiya_sys_jointeam",
                "PackagedFile": null
              }
            ],
            "Media": [
              {
                "MediaId": 235113034,
                "MediaPathName": "Media/ko/235113034.wem",
                "PrefetchSize": 0,
                "MemoryAlignment": 16,
                "bDeviceMemory": false,
                "bStreaming": true,
                "DebugName": "role\\branch_2,4\\katixiya\\ko_vo_katixiya_sys_jointeam_03_word.wav",
                "PackagedFile": null
              },
              {
                "MediaId": 316453704,
                "MediaPathName": "Media/ko/316453704.wem",
                "PrefetchSize": 0,
                "MemoryAlignment": 16,
                "bDeviceMemory": false,
                "bStreaming": true,
                "DebugName": "role\\branch_2,4\\katixiya\\ko_vo_katixiya_sys_jointeam_02_word.wav",
                "PackagedFile": null
              },
              {
                "MediaId": 610628034,
                "MediaPathName": "Media/610628034.wem",
                "PrefetchSize": 0,
                "MemoryAlignment": 16,
                "bDeviceMemory": false,
                "bStreaming": true,
                "DebugName": "SFX\\UI\\sfx_ui_com\\ui_fx_spl_team_role_choose1.wav",
                "PackagedFile": null
              },
              {
                "MediaId": 732948281,
                "MediaPathName": "Media/ko/732948281.wem",
                "PrefetchSize": 0,
                "MemoryAlignment": 16,
                "bDeviceMemory": false,
                "bStreaming": true,
                "DebugName": "role\\branch_2,4\\katixiya\\ko_vo_katixiya_sys_jointeam_01_word.wav",
                "PackagedFile": null
              }
            ],
            "ExternalSources": [],
            "SwitchContainerLeaves": [],
            "RequiredGroupValueSet": [],
            "DestroyOptions": "EWwiseEventDestroyOptions::StopEventOnDestroy",
            "DebugName": "play_vo_katixiya_sys_jointeam"
          }
        },
        {
          "Key": {
            "LanguageId": 1467418007,
            "LanguageName": "zh",
            "LanguageRequirement": "EWwiseLanguageRequirement::IsDefault"
          },
          "Value": {
            "EventId": 2827152122,
            "SoundBanks": [
              {
                "SoundBankId": 2827152122,
                "SoundBankPathName": "Event/zh/play_vo_katixiya_sys_jointeam.bnk",
                "MemoryAlignment": 16,
                "bDeviceMemory": false,
                "bContainsMedia": false,
                "SoundBankType": "EWwiseSoundBankType::Event",
                "DebugName": "play_vo_katixiya_sys_jointeam",
                "PackagedFile": null
              }
            ],
            "Media": [
              {
                "MediaId": 112951723,
                "MediaPathName": "Media/zh/112951723.wem",
                "PrefetchSize": 0,
                "MemoryAlignment": 16,
                "bDeviceMemory": false,
                "bStreaming": true,
                "DebugName": "role\\branch_2,4\\katixiya\\zh_vo_katixiya_sys_jointeam_03_word.wav",
                "PackagedFile": null
              },
              {
                "MediaId": 479264018,
                "MediaPathName": "Media/zh/479264018.wem",
                "PrefetchSize": 0,
                "MemoryAlignment": 16,
                "bDeviceMemory": false,
                "bStreaming": true,
                "DebugName": "role\\branch_2,4\\katixiya\\zh_vo_katixiya_sys_jointeam_01_word.wav",
                "PackagedFile": null
              },
              {
                "MediaId": 610628034,
                "MediaPathName": "Media/610628034.wem",
                "PrefetchSize": 0,
                "MemoryAlignment": 16,
                "bDeviceMemory": false,
                "bStreaming": true,
                "DebugName": "SFX\\UI\\sfx_ui_com\\ui_fx_spl_team_role_choose1.wav",
                "PackagedFile": null
              },
              {
                "MediaId": 630301217,
                "MediaPathName": "Media/zh/630301217.wem",
                "PrefetchSize": 0,
                "MemoryAlignment": 16,
                "bDeviceMemory": false,
                "bStreaming": true,
                "DebugName": "role\\branch_2,4\\katixiya\\zh_vo_katixiya_sys_jointeam_02_word.wav",
                "PackagedFile": null
              }
            ],
            "ExternalSources": [],
            "SwitchContainerLeaves": [],
            "RequiredGroupValueSet": [],
            "DestroyOptions": "EWwiseEventDestroyOptions::StopEventOnDestroy",
            "DebugName": "play_vo_katixiya_sys_jointeam"
          }
        }
      ],
      "DebugName": "play_vo_katixiya_sys_jointeam",
      "EventId": 2827152122
    },
    "MaximumDuration": 4.6925626,
    "MinimumDuration": 4.6925626,
    "IsInfinite": false,
    "MaxAttenuationRadius": 0.0
  }
]