[
  {
    "Type": "AkAudioEvent",
    "Name": "play_sfx_gp_carchase_zc_missilefly_long",
    "Flags": "RF_Public | RF_Transactional | RF_WasLoaded | RF_LoadCompleted",
    "Class": "UScriptClass'AkAudioEvent'",
    "Package": "Client/Content/Aki/WwiseAudio/Events/play_sfx_gp_carchase_zc_missilefly_long",
    "EventCookedData": {
      "EventLanguageMap": [
        {
          "Key": {
            "LanguageId": 0,
            "LanguageName": "SFX",
            "LanguageRequirement": "EWwiseLanguageRequirement::SFX"
          },
          "Value": {
            "EventId": 1764768241,
            "SoundBanks": [
              {
                "SoundBankId": 1764768241,
                "SoundBankPathName": "Event/play_sfx_gp_carchase_zc_missilefly_long.bnk",
                "MemoryAlignment": 16,
                "bDeviceMemory": false,
                "bContainsMedia": false,
                "SoundBankType": "EWwiseSoundBankType::Event",
                "DebugName": "play_sfx_gp_carchase_zc_missilefly_long",
                "PackagedFile": null
              }
            ],
            "Media": [
              {
                "MediaId": 274736978,
                "MediaPathName": "Media/274736978.wem",
                "PrefetchSize": 0,
                "MemoryAlignment": 16,
                "bDeviceMemory": false,
                "bStreaming": true,
                "DebugName": "SFX\\Interaction\\3.4\\sfx_gp_carchase_zc_missilefly_long01.wav",
                "PackagedFile": null
              },
              {
                "MediaId": 752112401,
                "MediaPathName": "Media/752112401.wem",
                "PrefetchSize": 0,
                "MemoryAlignment": 16,
                "bDeviceMemory": false,
                "bStreaming": true,
                "DebugName": "SFX\\Enemy\\Boss\\Qishi\\new\\boss_qishi_stage2_fx_attack09_fire.wav",
                "PackagedFile": null
              }
            ],
            "ExternalSources": [],
            "SwitchContainerLeaves": [],
            "RequiredGroupValueSet": [],
            "DestroyOptions": "EWwiseEventDestroyOptions::StopEventOnDestroy",
            "DebugName": "play_sfx_gp_carchase_zc_missilefly_long"
          }
        }
      ],
      "DebugName": "play_sfx_gp_carchase_zc_missilefly_long",
      "EventId": 1764768241
    },
    "MaximumDuration": 6.235083,
    "MinimumDuration": 6.235083,
    "IsInfinite": false,
    "MaxAttenuationRadius": 0.0
  }
]