[
  {
    "Type": "AkAudioEvent",
    "Name": "play_favor_vo_lingyang_scan",
    "Flags": "RF_Public | RF_Transactional | RF_WasLoaded | RF_LoadCompleted",
    "Class": "UScriptClass'AkAudioEvent'",
    "Package": "Client/Content/Aki/WwiseAudio/Events/play_favor_vo_lingyang_scan",
    "EventCookedData": {
      "EventLanguageMap": [
        {
          "Key": {
            "LanguageId": 0,
            "LanguageName": "SFX",
            "LanguageRequirement": "EWwiseLanguageRequirement::SFX"
          },
          "Value": {
            "EventId": 1734876452,
            "SoundBanks": [
              {
                "SoundBankId": 1734876452,
                "SoundBankPathName": "Event/play_favor_vo_lingyang_scan.bnk",
                "MemoryAlignment": 16,
                "bDeviceMemory": false,
                "bContainsMedia": false,
                "SoundBankType": "EWwiseSoundBankType::Event",
                "DebugName": "play_favor_vo_lingyang_scan",
                "PackagedFile": null
              }
            ],
            "Media": [
              {
                "MediaId": 276764731,
                "MediaPathName": "Media/276764731.wem",
                "PrefetchSize": 0,
                "MemoryAlignment": 16,
                "bDeviceMemory": false,
                "bStreaming": false,
                "DebugName": "Voices\\zh\\role\\branch_1,0\\lingyang\\zh_vo_lingyang_scan.wav",
                "PackagedFile": null
              },
              {
                "MediaId": 296772040,
                "MediaPathName": "Media/296772040.wem",
                "PrefetchSize": 0,
                "MemoryAlignment": 16,
                "bDeviceMemory": false,
                "bStreaming": false,
                "DebugName": "Voices\\ko\\role\\branch_1,0\\lingyang\\ko_vo_lingyang_scan.wav",
                "PackagedFile": null
              },
              {
                "MediaId": 599032770,
                "MediaPathName": "Media/599032770.wem",
                "PrefetchSize": 0,
                "MemoryAlignment": 16,
                "bDeviceMemory": false,
                "bStreaming": false,
                "DebugName": "Voices\\ja\\role\\branch_1,0\\lingyang\\ja_vo_lingyang_scan.wav",
                "PackagedFile": null
              },
              {
                "MediaId": 630108823,
                "MediaPathName": "Media/630108823.wem",
                "PrefetchSize": 0,
                "MemoryAlignment": 16,
                "bDeviceMemory": false,
                "bStreaming": false,
                "DebugName": "Voices\\en\\role\\branch_1,0\\lingyang\\en_vo_lingyang_scan.wav",
                "PackagedFile": null
              }
            ],
            "ExternalSources": [],
            "SwitchContainerLeaves": [],
            "RequiredGroupValueSet": [],
            "DestroyOptions": "EWwiseEventDestroyOptions::StopEventOnDestroy",
            "DebugName": "play_favor_vo_lingyang_scan"
          }
        }
      ],
      "DebugName": "play_favor_vo_lingyang_scan",
      "EventId": 1734876452
    },
    "MaximumDuration": 0.9304375,
    "MinimumDuration": 0.9304375,
    "IsInfinite": false,
    "MaxAttenuationRadius": 0.0
  }
]