[
  {
    "Type": "AkAudioEvent",
    "Name": "play_vo_jianxin_skill02",
    "Flags": "RF_Public | RF_Transactional | RF_WasLoaded | RF_LoadCompleted",
    "Class": "UScriptClass'AkAudioEvent'",
    "Package": "Client/Content/Aki/WwiseAudio/Events/play_vo_jianxin_skill02",
    "EventCookedData": {
      "EventLanguageMap": [
        {
          "Key": {
            "LanguageId": 1819748192,
            "LanguageName": "en",
            "LanguageRequirement": "EWwiseLanguageRequirement::IsOptional"
          },
          "Value": {
            "EventId": 3517078881,
            "SoundBanks": [
              {
                "SoundBankId": 3517078881,
                "SoundBankPathName": "Event/en/play_vo_jianxin_skill02.bnk",
                "MemoryAlignment": 16,
                "bDeviceMemory": false,
                "bContainsMedia": false,
                "SoundBankType": "EWwiseSoundBankType::Event",
                "DebugName": "play_vo_jianxin_skill02",
                "PackagedFile": null
              }
            ],
            "Media": [
              {
                "MediaId": 732107301,
                "MediaPathName": "Media/en/732107301.wem",
                "PrefetchSize": 0,
                "MemoryAlignment": 16,
                "bDeviceMemory": false,
                "bStreaming": true,
                "DebugName": "role\\branch_1_0\\jianxin\\vo_jianxin_skill02.wav",
                "PackagedFile": null
              }
            ],
            "ExternalSources": [],
            "SwitchContainerLeaves": [],
            "RequiredGroupValueSet": [],
            "DestroyOptions": "EWwiseEventDestroyOptions::StopEventOnDestroy",
            "DebugName": "play_vo_jianxin_skill02"
          }
        },
        {
          "Key": {
            "LanguageId": 1735860046,
            "LanguageName": "ja",
            "LanguageRequirement": "EWwiseLanguageRequirement::IsOptional"
          },
          "Value": {
            "EventId": 3517078881,
            "SoundBanks": [
              {
                "SoundBankId": 3517078881,
                "SoundBankPathName": "Event/ja/play_vo_jianxin_skill02.bnk",
                "MemoryAlignment": 16,
                "bDeviceMemory": false,
                "bContainsMedia": false,
                "SoundBankType": "EWwiseSoundBankType::Event",
                "DebugName": "play_vo_jianxin_skill02",
                "PackagedFile": null
              }
            ],
            "Media": [
              {
                "MediaId": 775892129,
                "MediaPathName": "Media/ja/775892129.wem",
                "PrefetchSize": 0,
                "MemoryAlignment": 16,
                "bDeviceMemory": false,
                "bStreaming": true,
                "DebugName": "role\\branch_1_0\\jianxin\\vo_jianxin_skill02.wav",
                "PackagedFile": null
              }
            ],
            "ExternalSources": [],
            "SwitchContainerLeaves": [],
            "RequiredGroupValueSet": [],
            "DestroyOptions": "EWwiseEventDestroyOptions::StopEventOnDestroy",
            "DebugName": "play_vo_jianxin_skill02"
          }
        },
        {
          "Key": {
            "LanguageId": 1719082483,
            "LanguageName": "ko",
            "LanguageRequirement": "EWwiseLanguageRequirement::IsOptional"
          },
          "Value": {
            "EventId": 3517078881,
            "SoundBanks": [
              {
                "SoundBankId": 3517078881,
                "SoundBankPathName": "Event/ko/play_vo_jianxin_skill02.bnk",
                "MemoryAlignment": 16,
                "bDeviceMemory": false,
                "bContainsMedia": false,
                "SoundBankType": "EWwiseSoundBankType::Event",
                "DebugName": "play_vo_jianxin_skill02",
                "PackagedFile": null
              }
            ],
            "Media": [
              {
                "MediaId": 1019491417,
                "MediaPathName": "Media/ko/1019491417.wem",
                "PrefetchSize": 0,
                "MemoryAlignment": 16,
                "bDeviceMemory": false,
                "bStreaming": true,
                "DebugName": "role\\branch_1_0\\jianxin\\vo_jianxin_skill02.wav",
                "PackagedFile": null
              }
            ],
            "ExternalSources": [],
            "SwitchContainerLeaves": [],
            "RequiredGroupValueSet": [],
            "DestroyOptions": "EWwiseEventDestroyOptions::StopEventOnDestroy",
            "DebugName": "play_vo_jianxin_skill02"
          }
        },
        {
          "Key": {
            "LanguageId": 1467418007,
            "LanguageName": "zh",
            "LanguageRequirement": "EWwiseLanguageRequirement::IsDefault"
          },
          "Value": {
            "EventId": 3517078881,
            "SoundBanks": [
              {
                "SoundBankId": 3517078881,
                "SoundBankPathName": "Event/zh/play_vo_jianxin_skill02.bnk",
                "MemoryAlignment": 16,
                "bDeviceMemory": false,
                "bContainsMedia": false,
                "SoundBankType": "EWwiseSoundBankType::Event",
                "DebugName": "play_vo_jianxin_skill02",
                "PackagedFile": null
              }
            ],
            "Media": [
              {
                "MediaId": 650161873,
                "MediaPathName": "Media/zh/650161873.wem",
                "PrefetchSize": 0,
                "MemoryAlignment": 16,
                "bDeviceMemory": false,
                "bStreaming": true,
                "DebugName": "role\\branch_1_0\\jianxin\\vo_jianxin_skill02.wav",
                "PackagedFile": null
              }
            ],
            "ExternalSources": [],
            "SwitchContainerLeaves": [],
            "RequiredGroupValueSet": [],
            "DestroyOptions": "EWwiseEventDestroyOptions::StopEventOnDestroy",
            "DebugName": "play_vo_jianxin_skill02"
          }
        }
      ],
      "DebugName": "play_vo_jianxin_skill02",
      "EventId": 3517078881
    },
    "MaximumDuration": 0.9771875,
    "MinimumDuration": 0.001,
    "IsInfinite": false,
    "MaxAttenuationRadius": 5000.0
  }
]