[
  {
    "Type": "AkAudioEvent",
    "Name": "play_vo_qianxiao_sys_rankup04",
    "Flags": "RF_Public | RF_Transactional | RF_WasLoaded | RF_LoadCompleted",
    "Class": "UScriptClass'AkAudioEvent'",
    "EventCookedData": {
      "EventLanguageMap": [
        {
          "Key": {
            "LanguageId": 1819748192,
            "LanguageName": "en",
            "LanguageRequirement": "EWwiseLanguageRequirement::IsOptional"
          },
          "Value": {
            "EventId": -1353936876,
            "SoundBanks": [
              {
                "SoundBankId": -1353936876,
                "SoundBankPathName": "Event/en/play_vo_qianxiao_sys_rankup04.bnk",
                "MemoryAlignment": 16,
                "bDeviceMemory": false,
                "bContainsMedia": false,
                "SoundBankType": "EWwiseSoundBankType::Event",
                "DebugName": "play_vo_qianxiao_sys_rankup04",
                "PackagedFile": null
              }
            ],
            "Media": [
              {
                "MediaId": 463213706,
                "MediaPathName": "Media/en/463213706.wem",
                "PrefetchSize": 0,
                "MemoryAlignment": 16,
                "bDeviceMemory": false,
                "bStreaming": true,
                "DebugName": "role\\branch_2,8\\qianxiao\\en_vo_qianxiao_sys_rankup04_word.wav",
                "PackagedFile": null
              }
            ],
            "ExternalSources": [],
            "SwitchContainerLeaves": [],
            "RequiredGroupValueSet": [],
            "DestroyOptions": "EWwiseEventDestroyOptions::StopEventOnDestroy",
            "DebugName": "play_vo_qianxiao_sys_rankup04"
          }
        },
        {
          "Key": {
            "LanguageId": 1735860046,
            "LanguageName": "ja",
            "LanguageRequirement": "EWwiseLanguageRequirement::IsOptional"
          },
          "Value": {
            "EventId": -1353936876,
            "SoundBanks": [
              {
                "SoundBankId": -1353936876,
                "SoundBankPathName": "Event/ja/play_vo_qianxiao_sys_rankup04.bnk",
                "MemoryAlignment": 16,
                "bDeviceMemory": false,
                "bContainsMedia": false,
                "SoundBankType": "EWwiseSoundBankType::Event",
                "DebugName": "play_vo_qianxiao_sys_rankup04",
                "PackagedFile": null
              }
            ],
            "Media": [
              {
                "MediaId": 486355382,
                "MediaPathName": "Media/ja/486355382.wem",
                "PrefetchSize": 0,
                "MemoryAlignment": 16,
                "bDeviceMemory": false,
                "bStreaming": true,
                "DebugName": "role\\branch_2,8\\qianxiao\\ja_vo_qianxiao_sys_rankup04_word.wav",
                "PackagedFile": null
              }
            ],
            "ExternalSources": [],
            "SwitchContainerLeaves": [],
            "RequiredGroupValueSet": [],
            "DestroyOptions": "EWwiseEventDestroyOptions::StopEventOnDestroy",
            "DebugName": "play_vo_qianxiao_sys_rankup04"
          }
        },
        {
          "Key": {
            "LanguageId": 1719082483,
            "LanguageName": "ko",
            "LanguageRequirement": "EWwiseLanguageRequirement::IsOptional"
          },
          "Value": {
            "EventId": -1353936876,
            "SoundBanks": [
              {
                "SoundBankId": -1353936876,
                "SoundBankPathName": "Event/ko/play_vo_qianxiao_sys_rankup04.bnk",
                "MemoryAlignment": 16,
                "bDeviceMemory": false,
                "bContainsMedia": false,
                "SoundBankType": "EWwiseSoundBankType::Event",
                "DebugName": "play_vo_qianxiao_sys_rankup04",
                "PackagedFile": null
              }
            ],
            "Media": [
              {
                "MediaId": 468168794,
                "MediaPathName": "Media/ko/468168794.wem",
                "PrefetchSize": 0,
                "MemoryAlignment": 16,
                "bDeviceMemory": false,
                "bStreaming": true,
                "DebugName": "role\\branch_2,8\\qianxiao\\ko_vo_qianxiao_sys_rankup04_word.wav",
                "PackagedFile": null
              }
            ],
            "ExternalSources": [],
            "SwitchContainerLeaves": [],
            "RequiredGroupValueSet": [],
            "DestroyOptions": "EWwiseEventDestroyOptions::StopEventOnDestroy",
            "DebugName": "play_vo_qianxiao_sys_rankup04"
          }
        },
        {
          "Key": {
            "LanguageId": 1467418007,
            "LanguageName": "zh",
            "LanguageRequirement": "EWwiseLanguageRequirement::IsDefault"
          },
          "Value": {
            "EventId": -1353936876,
            "SoundBanks": [
              {
                "SoundBankId": -1353936876,
                "SoundBankPathName": "Event/zh/play_vo_qianxiao_sys_rankup04.bnk",
                "MemoryAlignment": 16,
                "bDeviceMemory": false,
                "bContainsMedia": false,
                "SoundBankType": "EWwiseSoundBankType::Event",
                "DebugName": "play_vo_qianxiao_sys_rankup04",
                "PackagedFile": null
              }
            ],
            "Media": [
              {
                "MediaId": 319081756,
                "MediaPathName": "Media/zh/319081756.wem",
                "PrefetchSize": 0,
                "MemoryAlignment": 16,
                "bDeviceMemory": false,
                "bStreaming": true,
                "DebugName": "role\\branch_2,8\\qianxiao\\zh_vo_qianxiao_sys_rankup04_word.wav",
                "PackagedFile": null
              }
            ],
            "ExternalSources": [],
            "SwitchContainerLeaves": [],
            "RequiredGroupValueSet": [],
            "DestroyOptions": "EWwiseEventDestroyOptions::StopEventOnDestroy",
            "DebugName": "play_vo_qianxiao_sys_rankup04"
          }
        }
      ],
      "DebugName": "play_vo_qianxiao_sys_rankup04",
      "EventId": -1353936876
    },
    "MaximumDuration": 11.074729,
    "MinimumDuration": 11.074729,
    "IsInfinite": false,
    "MaxAttenuationRadius": 0.0
  }
]