[
  {
    "Type": "AkAudioEvent",
    "Name": "play_plot_hit_feedback_9_23",
    "Class": "UScriptClass'AkAudioEvent'",
    "Flags": "RF_Public | RF_Transactional | RF_WasLoaded | RF_LoadCompleted",
    "EventCookedData": {
      "EventLanguageMap": [
        {
          "Key": {
            "LanguageId": 0,
            "LanguageName": "SFX",
            "LanguageRequirement": "EWwiseLanguageRequirement::SFX"
          },
          "Value": {
            "EventId": 508667245,
            "SoundBanks": [
              {
                "SoundBankId": 508667245,
                "SoundBankPathName": "Event/play_plot_hit_feedback_9_23.bnk",
                "MemoryAlignment": 16,
                "bDeviceMemory": false,
                "bContainsMedia": false,
                "SoundBankType": "EWwiseSoundBankType::Event",
                "DebugName": "play_plot_hit_feedback_9_23"
              }
            ],
            "Media": [
              {
                "MediaId": 94554589,
                "MediaPathName": "Media/94554589.wem",
                "PrefetchSize": 0,
                "MemoryAlignment": 16,
                "bDeviceMemory": false,
                "bStreaming": false,
                "DebugName": "plot_hit_feedback_9_23\\plot_hit_feedback_9_23_05.wav"
              },
              {
                "MediaId": 443152084,
                "MediaPathName": "Media/443152084.wem",
                "PrefetchSize": 0,
                "MemoryAlignment": 16,
                "bDeviceMemory": false,
                "bStreaming": false,
                "DebugName": "plot_hit_feedback_9_23\\plot_hit_feedback_9_23_06.wav"
              },
              {
                "MediaId": 496279938,
                "MediaPathName": "Media/496279938.wem",
                "PrefetchSize": 0,
                "MemoryAlignment": 16,
                "bDeviceMemory": false,
                "bStreaming": false,
                "DebugName": "plot_hit_feedback_9_23\\plot_hit_feedback_9_23_04.wav"
              },
              {
                "MediaId": 527199901,
                "MediaPathName": "Media/527199901.wem",
                "PrefetchSize": 0,
                "MemoryAlignment": 16,
                "bDeviceMemory": false,
                "bStreaming": false,
                "DebugName": "plot_hit_feedback_9_23\\plot_hit_feedback_9_23_03.wav"
              },
              {
                "MediaId": 682356614,
                "MediaPathName": "Media/682356614.wem",
                "PrefetchSize": 0,
                "MemoryAlignment": 16,
                "bDeviceMemory": false,
                "bStreaming": false,
                "DebugName": "plot_hit_feedback_9_23\\plot_hit_feedback_9_23_01.wav"
              },
              {
                "MediaId": 985664529,
                "MediaPathName": "Media/985664529.wem",
                "PrefetchSize": 0,
                "MemoryAlignment": 16,
                "bDeviceMemory": false,
                "bStreaming": false,
                "DebugName": "plot_hit_feedback_9_23\\plot_hit_feedback_9_23_02.wav"
              }
            ],
            "ExternalSources": [],
            "SwitchContainerLeaves": [],
            "RequiredGroupValueSet": [],
            "DestroyOptions": "EWwiseEventDestroyOptions::StopEventOnDestroy",
            "DebugName": "play_plot_hit_feedback_9_23"
          }
        }
      ],
      "DebugName": "play_plot_hit_feedback_9_23",
      "EventId": 508667245
    },
    "MaximumDuration": 0.87987816,
    "MinimumDuration": 0.5653333,
    "IsInfinite": false,
    "MaxAttenuationRadius": 0.0
  }
]