[
  {
    "Type": "AkAudioEvent",
    "Name": "play_favor_word_nvzhu_atk06_01",
    "Class": "UScriptClass'AkAudioEvent'",
    "Flags": "RF_Public | RF_Transactional | RF_WasLoaded | RF_LoadCompleted",
    "EventCookedData": {
      "EventLanguageMap": [
        {
          "Key": {
            "LanguageId": 1819748192,
            "LanguageName": "en",
            "LanguageRequirement": "EWwiseLanguageRequirement::IsOptional"
          },
          "Value": {
            "EventId": 102460736,
            "SoundBanks": [
              {
                "SoundBankId": 102460736,
                "SoundBankPathName": "Event/en/play_favor_word_nvzhu_atk06_01.bnk",
                "MemoryAlignment": 16,
                "bDeviceMemory": false,
                "bContainsMedia": false,
                "SoundBankType": "EWwiseSoundBankType::Event",
                "DebugName": "play_favor_word_nvzhu_atk06_01"
              }
            ],
            "Media": [
              {
                "MediaId": 475361454,
                "MediaPathName": "Media/en/475361454.wem",
                "PrefetchSize": 0,
                "MemoryAlignment": 16,
                "bDeviceMemory": false,
                "bStreaming": true,
                "DebugName": "role\\branch_1_0\\nvzhu\\vo_nvzhu_atk06_01.wav"
              }
            ],
            "ExternalSources": [],
            "SwitchContainerLeaves": [],
            "RequiredGroupValueSet": [],
            "DestroyOptions": "EWwiseEventDestroyOptions::StopEventOnDestroy",
            "DebugName": "play_favor_word_nvzhu_atk06_01"
          }
        },
        {
          "Key": {
            "LanguageId": 1735860046,
            "LanguageName": "ja",
            "LanguageRequirement": "EWwiseLanguageRequirement::IsOptional"
          },
          "Value": {
            "EventId": 102460736,
            "SoundBanks": [
              {
                "SoundBankId": 102460736,
                "SoundBankPathName": "Event/ja/play_favor_word_nvzhu_atk06_01.bnk",
                "MemoryAlignment": 16,
                "bDeviceMemory": false,
                "bContainsMedia": false,
                "SoundBankType": "EWwiseSoundBankType::Event",
                "DebugName": "play_favor_word_nvzhu_atk06_01"
              }
            ],
            "Media": [
              {
                "MediaId": 321268623,
                "MediaPathName": "Media/ja/321268623.wem",
                "PrefetchSize": 0,
                "MemoryAlignment": 16,
                "bDeviceMemory": false,
                "bStreaming": true,
                "DebugName": "role\\branch_1_0\\nvzhu\\vo_nvzhu_atk06_01.wav"
              }
            ],
            "ExternalSources": [],
            "SwitchContainerLeaves": [],
            "RequiredGroupValueSet": [],
            "DestroyOptions": "EWwiseEventDestroyOptions::StopEventOnDestroy",
            "DebugName": "play_favor_word_nvzhu_atk06_01"
          }
        },
        {
          "Key": {
            "LanguageId": 1719082483,
            "LanguageName": "ko",
            "LanguageRequirement": "EWwiseLanguageRequirement::IsOptional"
          },
          "Value": {
            "EventId": 102460736,
            "SoundBanks": [
              {
                "SoundBankId": 102460736,
                "SoundBankPathName": "Event/ko/play_favor_word_nvzhu_atk06_01.bnk",
                "MemoryAlignment": 16,
                "bDeviceMemory": false,
                "bContainsMedia": false,
                "SoundBankType": "EWwiseSoundBankType::Event",
                "DebugName": "play_favor_word_nvzhu_atk06_01"
              }
            ],
            "Media": [
              {
                "MediaId": 419462096,
                "MediaPathName": "Media/ko/419462096.wem",
                "PrefetchSize": 0,
                "MemoryAlignment": 16,
                "bDeviceMemory": false,
                "bStreaming": true,
                "DebugName": "role\\branch_1_0\\nvzhu\\vo_nvzhu_atk06_01.wav"
              }
            ],
            "ExternalSources": [],
            "SwitchContainerLeaves": [],
            "RequiredGroupValueSet": [],
            "DestroyOptions": "EWwiseEventDestroyOptions::StopEventOnDestroy",
            "DebugName": "play_favor_word_nvzhu_atk06_01"
          }
        },
        {
          "Key": {
            "LanguageId": 1467418007,
            "LanguageName": "zh",
            "LanguageRequirement": "EWwiseLanguageRequirement::IsDefault"
          },
          "Value": {
            "EventId": 102460736,
            "SoundBanks": [
              {
                "SoundBankId": 102460736,
                "SoundBankPathName": "Event/zh/play_favor_word_nvzhu_atk06_01.bnk",
                "MemoryAlignment": 16,
                "bDeviceMemory": false,
                "bContainsMedia": false,
                "SoundBankType": "EWwiseSoundBankType::Event",
                "DebugName": "play_favor_word_nvzhu_atk06_01"
              }
            ],
            "Media": [
              {
                "MediaId": 387960527,
                "MediaPathName": "Media/zh/387960527.wem",
                "PrefetchSize": 0,
                "MemoryAlignment": 16,
                "bDeviceMemory": false,
                "bStreaming": true,
                "DebugName": "role\\branch_1_0\\nvzhu\\vo_nvzhu_atk06_01.wav"
              }
            ],
            "ExternalSources": [],
            "SwitchContainerLeaves": [],
            "RequiredGroupValueSet": [],
            "DestroyOptions": "EWwiseEventDestroyOptions::StopEventOnDestroy",
            "DebugName": "play_favor_word_nvzhu_atk06_01"
          }
        }
      ],
      "DebugName": "play_favor_word_nvzhu_atk06_01",
      "EventId": 102460736
    },
    "MaximumDuration": 0.77216667,
    "MinimumDuration": 0.77216667,
    "IsInfinite": false,
    "MaxAttenuationRadius": 0.0
  }
]