[
  {
    "Type": "AkAudioEvent",
    "Name": "play_amb_role_interact_ice_click",
    "Flags": "RF_Public | RF_Transactional | RF_WasLoaded | RF_LoadCompleted",
    "Class": "UScriptClass'AkAudioEvent'",
    "Package": "Client/Content/Aki/WwiseAudio/Events/play_amb_role_interact_ice_click",
    "EventCookedData": {
      "EventLanguageMap": [
        {
          "Key": {
            "LanguageId": 0,
            "LanguageName": "SFX",
            "LanguageRequirement": "EWwiseLanguageRequirement::SFX"
          },
          "Value": {
            "EventId": 2661842575,
            "SoundBanks": [
              {
                "SoundBankId": 2661842575,
                "SoundBankPathName": "Event/play_amb_role_interact_ice_click.bnk",
                "MemoryAlignment": 16,
                "bDeviceMemory": false,
                "bContainsMedia": false,
                "SoundBankType": "EWwiseSoundBankType::Event",
                "DebugName": "play_amb_role_interact_ice_click",
                "PackagedFile": null
              }
            ],
            "Media": [
              {
                "MediaId": 189836724,
                "MediaPathName": "Media/189836724.wem",
                "PrefetchSize": 0,
                "MemoryAlignment": 16,
                "bDeviceMemory": false,
                "bStreaming": false,
                "DebugName": "not_in_folder/role_interact_ice_click_02.wav",
                "PackagedFile": null
              },
              {
                "MediaId": 280205703,
                "MediaPathName": "Media/280205703.wem",
                "PrefetchSize": 0,
                "MemoryAlignment": 16,
                "bDeviceMemory": false,
                "bStreaming": false,
                "DebugName": "not_in_folder/role_interact_ice_click_04.wav",
                "PackagedFile": null
              },
              {
                "MediaId": 473364637,
                "MediaPathName": "Media/473364637.wem",
                "PrefetchSize": 0,
                "MemoryAlignment": 16,
                "bDeviceMemory": false,
                "bStreaming": false,
                "DebugName": "not_in_folder/role_interact_ice_click_01.wav",
                "PackagedFile": null
              },
              {
                "MediaId": 597382435,
                "MediaPathName": "Media/597382435.wem",
                "PrefetchSize": 0,
                "MemoryAlignment": 16,
                "bDeviceMemory": false,
                "bStreaming": false,
                "DebugName": "not_in_folder/role_interact_ice_click_03.wav",
                "PackagedFile": null
              },
              {
                "MediaId": 782965074,
                "MediaPathName": "Media/782965074.wem",
                "PrefetchSize": 0,
                "MemoryAlignment": 16,
                "bDeviceMemory": false,
                "bStreaming": false,
                "DebugName": "not_in_folder/role_interact_ice_click_05.wav",
                "PackagedFile": null
              }
            ],
            "ExternalSources": [],
            "SwitchContainerLeaves": [],
            "RequiredGroupValueSet": [],
            "DestroyOptions": "EWwiseEventDestroyOptions::StopEventOnDestroy",
            "DebugName": "play_amb_role_interact_ice_click"
          }
        }
      ],
      "DebugName": "play_amb_role_interact_ice_click",
      "EventId": 2661842575
    },
    "MaximumDuration": 0.028520834,
    "MinimumDuration": 0.014166667,
    "IsInfinite": false,
    "MaxAttenuationRadius": 5000.0
  }
]