[
  {
    "Type": "AkAudioEvent",
    "Name": "play_favor_word_kakaluo_heavyatk01_03",
    "Class": "UScriptClass'AkAudioEvent'",
    "Flags": "RF_Public | RF_Transactional | RF_WasLoaded | RF_LoadCompleted",
    "EventCookedData": {
      "EventLanguageMap": [
        {
          "Key": {
            "LanguageId": 1819748192,
            "LanguageName": "en",
            "LanguageRequirement": "EWwiseLanguageRequirement::IsOptional"
          },
          "Value": {
            "EventId": 435656213,
            "SoundBanks": [
              {
                "SoundBankId": 435656213,
                "SoundBankPathName": "Event/en/play_favor_word_kakaluo_heavyatk01_03.bnk",
                "MemoryAlignment": 16,
                "bDeviceMemory": false,
                "bContainsMedia": false,
                "SoundBankType": "EWwiseSoundBankType::Event",
                "DebugName": "play_favor_word_kakaluo_heavyatk01_03",
                "PackagedFile": null
              }
            ],
            "Media": [
              {
                "MediaId": 703573367,
                "MediaPathName": "Media/en/703573367.wem",
                "PrefetchSize": 0,
                "MemoryAlignment": 16,
                "bDeviceMemory": false,
                "bStreaming": true,
                "DebugName": "role\\branch_1_0\\kakaluo\\vo_kakaluo_heavyatk01_03.wav",
                "PackagedFile": null
              }
            ],
            "ExternalSources": [],
            "SwitchContainerLeaves": [],
            "RequiredGroupValueSet": [],
            "DestroyOptions": "EWwiseEventDestroyOptions::StopEventOnDestroy",
            "DebugName": "play_favor_word_kakaluo_heavyatk01_03"
          }
        },
        {
          "Key": {
            "LanguageId": 1735860046,
            "LanguageName": "ja",
            "LanguageRequirement": "EWwiseLanguageRequirement::IsOptional"
          },
          "Value": {
            "EventId": 435656213,
            "SoundBanks": [
              {
                "SoundBankId": 435656213,
                "SoundBankPathName": "Event/ja/play_favor_word_kakaluo_heavyatk01_03.bnk",
                "MemoryAlignment": 16,
                "bDeviceMemory": false,
                "bContainsMedia": false,
                "SoundBankType": "EWwiseSoundBankType::Event",
                "DebugName": "play_favor_word_kakaluo_heavyatk01_03",
                "PackagedFile": null
              }
            ],
            "Media": [
              {
                "MediaId": 845614384,
                "MediaPathName": "Media/ja/845614384.wem",
                "PrefetchSize": 0,
                "MemoryAlignment": 16,
                "bDeviceMemory": false,
                "bStreaming": true,
                "DebugName": "role\\branch_1_0\\kakaluo\\vo_kakaluo_heavyatk01_03.wav",
                "PackagedFile": null
              }
            ],
            "ExternalSources": [],
            "SwitchContainerLeaves": [],
            "RequiredGroupValueSet": [],
            "DestroyOptions": "EWwiseEventDestroyOptions::StopEventOnDestroy",
            "DebugName": "play_favor_word_kakaluo_heavyatk01_03"
          }
        },
        {
          "Key": {
            "LanguageId": 1719082483,
            "LanguageName": "ko",
            "LanguageRequirement": "EWwiseLanguageRequirement::IsOptional"
          },
          "Value": {
            "EventId": 435656213,
            "SoundBanks": [
              {
                "SoundBankId": 435656213,
                "SoundBankPathName": "Event/ko/play_favor_word_kakaluo_heavyatk01_03.bnk",
                "MemoryAlignment": 16,
                "bDeviceMemory": false,
                "bContainsMedia": false,
                "SoundBankType": "EWwiseSoundBankType::Event",
                "DebugName": "play_favor_word_kakaluo_heavyatk01_03",
                "PackagedFile": null
              }
            ],
            "Media": [
              {
                "MediaId": 199677805,
                "MediaPathName": "Media/ko/199677805.wem",
                "PrefetchSize": 0,
                "MemoryAlignment": 16,
                "bDeviceMemory": false,
                "bStreaming": true,
                "DebugName": "role\\branch_1_0\\kakaluo\\vo_kakaluo_heavyatk01_03.wav",
                "PackagedFile": null
              }
            ],
            "ExternalSources": [],
            "SwitchContainerLeaves": [],
            "RequiredGroupValueSet": [],
            "DestroyOptions": "EWwiseEventDestroyOptions::StopEventOnDestroy",
            "DebugName": "play_favor_word_kakaluo_heavyatk01_03"
          }
        },
        {
          "Key": {
            "LanguageId": 1467418007,
            "LanguageName": "zh",
            "LanguageRequirement": "EWwiseLanguageRequirement::IsDefault"
          },
          "Value": {
            "EventId": 435656213,
            "SoundBanks": [
              {
                "SoundBankId": 435656213,
                "SoundBankPathName": "Event/zh/play_favor_word_kakaluo_heavyatk01_03.bnk",
                "MemoryAlignment": 16,
                "bDeviceMemory": false,
                "bContainsMedia": false,
                "SoundBankType": "EWwiseSoundBankType::Event",
                "DebugName": "play_favor_word_kakaluo_heavyatk01_03",
                "PackagedFile": null
              }
            ],
            "Media": [
              {
                "MediaId": 279730319,
                "MediaPathName": "Media/zh/279730319.wem",
                "PrefetchSize": 0,
                "MemoryAlignment": 16,
                "bDeviceMemory": false,
                "bStreaming": true,
                "DebugName": "role\\branch_1_0\\kakaluo\\vo_kakaluo_heavyatk01_03.wav",
                "PackagedFile": null
              }
            ],
            "ExternalSources": [],
            "SwitchContainerLeaves": [],
            "RequiredGroupValueSet": [],
            "DestroyOptions": "EWwiseEventDestroyOptions::StopEventOnDestroy",
            "DebugName": "play_favor_word_kakaluo_heavyatk01_03"
          }
        }
      ],
      "DebugName": "play_favor_word_kakaluo_heavyatk01_03",
      "EventId": 435656213
    },
    "MaximumDuration": 0.439375,
    "MinimumDuration": 0.439375,
    "IsInfinite": false,
    "MaxAttenuationRadius": 0.0
  }
]