[
  {
    "Type": "AkAudioEvent",
    "Name": "play_boss_wuguanzhe_bat_s2_atk10_cast",
    "Class": "UScriptClass'AkAudioEvent'",
    "Flags": "RF_Public | RF_Transactional | RF_WasLoaded | RF_LoadCompleted",
    "EventCookedData": {
      "EventLanguageMap": [
        {
          "Key": {
            "LanguageId": 0,
            "LanguageName": "SFX",
            "LanguageRequirement": "EWwiseLanguageRequirement::SFX"
          },
          "Value": {
            "EventId": 1832490682,
            "SoundBanks": [
              {
                "SoundBankId": 1832490682,
                "SoundBankPathName": "Event/play_boss_wuguanzhe_bat_s2_atk10_cast.bnk",
                "MemoryAlignment": 16,
                "bDeviceMemory": false,
                "bContainsMedia": false,
                "SoundBankType": "EWwiseSoundBankType::Event",
                "DebugName": "play_boss_wuguanzhe_bat_s2_atk10_cast",
                "PackagedFile": null
              }
            ],
            "Media": [
              {
                "MediaId": 904879732,
                "MediaPathName": "Media/904879732.wem",
                "PrefetchSize": 0,
                "MemoryAlignment": 16,
                "bDeviceMemory": false,
                "bStreaming": false,
                "DebugName": "SFX\\Enemy\\Boss\\wuguanzhe\\boss_wuguanzhe_bat_s2_atk10_cast.wav",
                "PackagedFile": null
              }
            ],
            "ExternalSources": [],
            "SwitchContainerLeaves": [],
            "RequiredGroupValueSet": [],
            "DestroyOptions": "EWwiseEventDestroyOptions::StopEventOnDestroy",
            "DebugName": "play_boss_wuguanzhe_bat_s2_atk10_cast"
          }
        }
      ],
      "DebugName": "play_boss_wuguanzhe_bat_s2_atk10_cast",
      "EventId": 1832490682
    },
    "MaximumDuration": 0.8261875,
    "MinimumDuration": 0.8261875,
    "IsInfinite": false,
    "MaxAttenuationRadius": 10000.0
  }
]