[
  {
    "Type": "AkAudioEvent",
    "Name": "set_story_music_mutouren_battle",
    "Flags": "RF_Public | RF_Transactional | RF_WasLoaded | RF_LoadCompleted",
    "Class": "UScriptClass'AkAudioEvent'",
    "Package": "Client/Content/Aki/WwiseAudio/Events/set_story_music_mutouren_battle",
    "EventCookedData": {
      "EventLanguageMap": [
        {
          "Key": {
            "LanguageId": 0,
            "LanguageName": "SFX",
            "LanguageRequirement": "EWwiseLanguageRequirement::SFX"
          },
          "Value": {
            "EventId": 2325300362,
            "SoundBanks": [
              {
                "SoundBankId": 2325300362,
                "SoundBankPathName": "Event/set_story_music_mutouren_battle.bnk",
                "MemoryAlignment": 16,
                "bDeviceMemory": false,
                "bContainsMedia": false,
                "SoundBankType": "EWwiseSoundBankType::Event",
                "DebugName": "set_story_music_mutouren_battle",
                "PackagedFile": null
              }
            ],
            "Media": [],
            "ExternalSources": [],
            "SwitchContainerLeaves": [],
            "RequiredGroupValueSet": [
              {
                "Type": "EWwiseGroupType::State",
                "GroupId": -1639194293,
                "Id": -1357134337,
                "DebugName": "battle"
              }
            ],
            "DestroyOptions": "EWwiseEventDestroyOptions::StopEventOnDestroy",
            "DebugName": "set_story_music_mutouren_battle"
          }
        }
      ],
      "DebugName": "set_story_music_mutouren_battle",
      "EventId": 2325300362
    },
    "MaximumDuration": 0.0,
    "MinimumDuration": 0.0,
    "IsInfinite": false,
    "MaxAttenuationRadius": 0.0
  }
]