[
  {
    "Type": "AkAudioEvent",
    "Name": "stop_amb_ui_suibowuyu_trainstation",
    "Flags": "RF_Public | RF_Transactional | RF_WasLoaded | RF_LoadCompleted",
    "Class": "UScriptClass'AkAudioEvent'",
    "Package": "Client/Content/Aki/WwiseAudio/Events/stop_amb_ui_suibowuyu_trainstation",
    "EventCookedData": {
      "EventLanguageMap": [
        {
          "Key": {
            "LanguageId": 0,
            "LanguageName": "SFX",
            "LanguageRequirement": "EWwiseLanguageRequirement::SFX"
          },
          "Value": {
            "EventId": 2340887299,
            "SoundBanks": [
              {
                "SoundBankId": 2340887299,
                "SoundBankPathName": "Event/stop_amb_ui_suibowuyu_trainstation.bnk",
                "MemoryAlignment": 16,
                "bDeviceMemory": false,
                "bContainsMedia": false,
                "SoundBankType": "EWwiseSoundBankType::Event",
                "DebugName": "stop_amb_ui_suibowuyu_trainstation",
                "PackagedFile": null
              }
            ],
            "Media": [],
            "ExternalSources": [],
            "SwitchContainerLeaves": [],
            "RequiredGroupValueSet": [],
            "DestroyOptions": "EWwiseEventDestroyOptions::StopEventOnDestroy",
            "DebugName": "stop_amb_ui_suibowuyu_trainstation"
          }
        }
      ],
      "DebugName": "stop_amb_ui_suibowuyu_trainstation",
      "EventId": 2340887299
    },
    "MaximumDuration": 0.0,
    "MinimumDuration": 0.0,
    "IsInfinite": false,
    "MaxAttenuationRadius": 0.0
  }
]