[
  {
    "Type": "AkAudioEvent",
    "Name": "ui_vision_equip_on",
    "Class": "UScriptClass'AkAudioEvent'",
    "Flags": "RF_Public | RF_Transactional | RF_WasLoaded | RF_LoadCompleted",
    "EventCookedData": {
      "EventLanguageMap": [
        {
          "Key": {
            "LanguageId": 0,
            "LanguageName": "SFX",
            "LanguageRequirement": "EWwiseLanguageRequirement::SFX"
          },
          "Value": {
            "EventId": 981146069,
            "SoundBanks": [
              {
                "SoundBankId": 981146069,
                "SoundBankPathName": "Event/ui_vision_equip_on.bnk",
                "MemoryAlignment": 16,
                "bDeviceMemory": false,
                "bContainsMedia": false,
                "SoundBankType": "EWwiseSoundBankType::Event",
                "DebugName": "ui_vision_equip_on"
              }
            ],
            "Media": [
              {
                "MediaId": 845707155,
                "MediaPathName": "Media/845707155.wem",
                "PrefetchSize": 0,
                "MemoryAlignment": 16,
                "bDeviceMemory": false,
                "bStreaming": false,
                "DebugName": "SFX\\UI\\sfx_ui_page\\ui_ia_spl_vision_equip.wav"
              }
            ],
            "ExternalSources": [],
            "SwitchContainerLeaves": [],
            "RequiredGroupValueSet": [],
            "DestroyOptions": "EWwiseEventDestroyOptions::StopEventOnDestroy",
            "DebugName": "ui_vision_equip_on"
          }
        }
      ],
      "DebugName": "ui_vision_equip_on",
      "EventId": 981146069
    },
    "MaximumDuration": 1.0388334,
    "MinimumDuration": 1.0388334,
    "IsInfinite": false,
    "MaxAttenuationRadius": 0.0
  }
]